vtuIO.py
VTUinterface-0.704.dist-info/LICENSE
VTUinterface-0.704.dist-info/METADATA
VTUinterface-0.704.dist-info/WHEEL
VTUinterface-0.704.dist-info/top_level.txt
VTUinterface-0.704.dist-info/RECORD
